[
  {
    "id": 1780562855180,
    "senderEmail": "petchpobpob@gmail.com",
    "receiverEmail": "janyamonnuamnoo@gmail.com",
    "text": "hello test",
    "timestamp": "2026-06-04T08:47:35.180Z",
    "isAccepted": true
  },
  {
    "id": 1780563070990,
    "senderEmail": "janyamonnuamnoo@gmail.com",
    "receiverEmail": "petchpobpob@gmail.com",
    "text": "hey, what up",
    "timestamp": "2026-06-04T08:51:10.990Z",
    "isAccepted": true
  },
  {
    "id": 1780563152051,
    "senderEmail": "janyamonnuamnoo@gmail.com",
    "receiverEmail": "petchpobpob@gmail.com",
    "text": "hi",
    "timestamp": "2026-06-04T08:52:32.051Z",
    "isAccepted": true
  },
  {
    "id": 1780563177462,
    "senderEmail": "petchpobpob@gmail.com",
    "receiverEmail": "janyamonnuamnoo@gmail.com",
    "text": "gcgucilgcgiclvviyl",
    "timestamp": "2026-06-04T08:52:57.462Z",
    "isAccepted": true
  },
  {
    "id": 1780563198260,
    "senderEmail": "petchpobpob@gmail.com",
    "receiverEmail": "janyamonnuamnoo@gmail.com",
    "text": "nigggh",
    "timestamp": "2026-06-04T08:53:18.260Z",
    "isAccepted": true
  },
  {
    "id": 1780805084181,
    "senderEmail": "petchpobpob@gmail.com",
    "receiverEmail": "janyamonnuamnoo@gmail.com",
    "text": "Hello",
    "timestamp": "2026-06-07T04:04:44.181Z",
    "isAccepted": true
  },
  {
    "id": 1780805087901,
    "senderEmail": "petchpobpob@gmail.com",
    "receiverEmail": "janyamonnuamnoo@gmail.com",
    "text": "big balck monkey boy",
    "timestamp": "2026-06-07T04:04:47.901Z",
    "isAccepted": true
  },
  {
    "id": 1780805717487,
    "senderEmail": "janyamonnuamnoo@gmail.com",
    "receiverEmail": "petchpobpob@gmail.com",
    "text": "Fuck you nigger",
    "timestamp": "2026-06-07T04:15:17.487Z",
    "isAccepted": true
  },
  {
    "id": 1780813172691,
    "senderEmail": "petchpobaaa@speede.com",
    "receiverEmail": "janyamonnuamnoo@gmail.com",
    "text": "สวัสดีครับ! ผมยอมรับใบสมัครสำหรับงาน \"big black monkey boi\" แล้วนะ สะดวกเริ่มงานเลยไหมครับ?",
    "timestamp": "2026-06-07T06:19:32.691Z",
    "isAccepted": false
  },
  {
    "id": 1780813197229,
    "senderEmail": "pobpetch@speede.com",
    "receiverEmail": "janyamonnuamnoo@gmail.com",
    "text": "สวัสดีครับ! ผมยอมรับใบสมัครสำหรับงาน \"ช่วยอมให้ฉันที\" แล้วนะ สะดวกเริ่มงานเลยไหมครับ?",
    "timestamp": "2026-06-07T06:19:57.229Z",
    "isAccepted": false
  },
  {
    "id": 1780831147276,
    "senderEmail": "janyamonnuamnoo@gmail.com",
    "receiverEmail": "janyamonnuamnoo@gmail.com",
    "text": "Hello big black monkey boi",
    "timestamp": "2026-06-07T11:19:07.276Z",
    "isAccepted": false
  }
]